json_exporter/__init__.py
json_exporter-0.0.1.dist-info/LICENSE
json_exporter-0.0.1.dist-info/METADATA
json_exporter-0.0.1.dist-info/WHEEL
json_exporter-0.0.1.dist-info/top_level.txt
json_exporter-0.0.1.dist-info/RECORD
