Metadata-Version: 2.1
Name: json-exporter
Version: 0.0.1
Summary: A Python library for exporting JSON data as metrics for Prometheus
Author-email: Desultory <dev@pyl.onl>
Classifier: Programming Language :: Python :: 3
Classifier: License :: OSI Approved :: GNU General Public License v2 (GPLv2)
Classifier: Operating System :: OS Independent
Requires-Python: >=3.9
License-File: LICENSE
Requires-Dist: zenlib >=1.1.1
